{
	"city":[
		{
			"id":1,
			"name":"Москва",
			"metro":[
				{
					"id":1,
					"name":"Авиамоторная",
					"latitude":55.751190924537,
					"longitude":37.716519279097,
					"operationTime": "C 10-00 до 200-00"
				},
				{
					"id":2,
					"name":"Автозаводская",
					"latitude":55.706645371814,
					"longitude":37.65708707968,
					"operationTime": "C 10-00 до 200-00"
				},
				{
					"id":3,
					"name":"Академическая",
					"latitude":55.687586442883,
					"longitude":37.573439070015,
					"operationTime": "C 10-00 до 200-00"
				},
				{
					"id":4,
					"name":"Александровский сад",
					"latitude":55.752165538687,
					"longitude":37.608942719573,
					"operationTime": "C 10-00 до 200-00"
				},
				{
					"id":5,
					"name":"Алексеевская",
					"latitude":55.807805319109,
					"longitude":37.638597025131,
					"operationTime": "C 10-00 до 200-00"
				},
				{
					"id":6,
					"name":"Алма-Атинская",
					"latitude":55.633478139151,
					"longitude":37.765602398147,
					"operationTime": "C 10-00 до 200-00"
				},
				{
					"id":7,
					"name":"Алтуфьево",
					"latitude":55.899015239215,
					"longitude":37.587891170639,
					"operationTime": "C 10-00 до 200-00"
				},
				{
					"id":8,
					"name":"Аннино",
					"latitude":55.583766664072,
					"longitude":37.596619380951,
					"operationTime": "C 10-00 до 200-00"
				},
				{
					"id":9,
					"name":"Арбатская (арбатско-покровская)",
					"latitude":55.752340305328,
					"longitude":37.604008211639,
					"operationTime": "C 10-00 до 200-00"
				},
				{
					"id":10,
					"name":"Арбатская (филевская)",
					"latitude":55.75209827389,
					"longitude":37.60152985051,
					"operationTime": "C 10-00 до 200-00"
				},
				{
					"id":11,
					"name":"Аэропорт",
					"latitude":55.801125459324,
					"longitude":37.532226769836,
					"operationTime": "C 10-00 до 200-00"
				},
				{
					"id":12,
					"name":"Бабушкинская",
					"latitude":55.870469406153,
					"longitude":37.665160857147,
					"operationTime": "C 10-00 до 200-00"
				},
				{
					"id":13,
					"name":"Багратионовская",
					"latitude":55.74359500536,
					"longitude":37.497218769836,
					"operationTime": "C 10-00 до 200-00"
				},
				{
					"id":14,
					"name":"Баррикадная",
					"latitude":55.760728035353,
					"longitude":37.5812805,
					"operationTime": "C 10-00 до 200-00"
				},
				{
					"id":15,
					"name":"Бауманская",
					"latitude":55.772357395997,
					"longitude":37.678874567459,
					"operationTime": "C 10-00 до 200-00"
				},
				{
					"id":16,
					"name":"Беговая",
					"latitude":55.773933645102,
					"longitude":37.544670921951,
					"operationTime": "C 10-00 до 200-00"
				},
				{
					"id":17,
					"name":"Белорусская",
					"latitude":55.775368259476,
					"longitude":37.582514509232,
					"operationTime": "C 10-00 до 200-00"
				},
				{
					"id":18,
					"name":"Беляево",
					"latitude":55.641525467909,
					"longitude":37.525964296295,
					"operationTime": "C 10-00 до 200-00"
				},
				{
					"id":19,
					"name":"Бибирево",
					"latitude":55.884326573938,
					"longitude":37.601487005279,
					"operationTime": "C 10-00 до 200-00"
				},
				{
					"id":20,
					"name":"Библиотека Ленина",
					"latitude":55.752561284565,
					"longitude":37.610751939148,
					"operationTime": "C 10-00 до 200-00"
				},
				{
					"id":21,
					"name":"Битцевский парк",
					"latitude":55.60006401744,
					"longitude":37.556079518524,
					"operationTime": "C 10-00 до 200-00"
				},
				{
					"id":22,
					"name":"Борисово",
					"latitude":55.634060176545,
					"longitude":37.744742451065,
					"operationTime": "C 10-00 до 200-00"
				},
				{
					"id":23,
					"name":"Боровицкая",
					"latitude":55.750502185627,
					"longitude":37.609017965607,
					"operationTime": "C 10-00 до 200-00"
				},
				{
					"id":24,
					"name":"Ботанический сад",
					"latitude":55.843938804926,
					"longitude":37.637607652115,
					"operationTime": "C 10-00 до 200-00"
				},
				{
					"id":78,
					"name":"Братиславская",
					"latitude":55.658967991016,
					"longitude":37.749784439148,
					"operationTime": "C 10-00 до 200-00"
				},
				{
					"id":81,
					"name":"Бульвар адмирала Ушакова",
					"latitude":55.545085117935,
					"longitude":37.541900346558,
					"operationTime": "C 10-00 до 200-00"
				},
				{
					"id":79,
					"name":"Бульвар Дмитрия Донского",
					"latitude":55.568500555371,
					"longitude":37.575961480148,
					"operationTime": "C 10-00 до 200-00"
				},
				{
					"id":80,
					"name":"Бульвар Рокоссовского",
					"latitude":55.814952958203,
					"longitude":37.73228408728,
					"operationTime": "C 10-00 до 200-00"
				},
				{
					"id":87,
					"name":"Бунинская Аллея",
					"latitude":55.537799506467,
					"longitude":37.515350371689,
					"operationTime": "C 10-00 до 200-00"
				},
				{
					"id":97,
					"name":"Варшавская",
					"latitude":55.65350002743,
					"longitude":37.617826343903,
					"operationTime": "C 10-00 до 200-00"
				},
				{
					"id":96,
					"name":"ВДНХ",
					"latitude":55.822282607628,
					"longitude":37.64149819577,
					"operationTime": "C 10-00 до 200-00"
				},
				{
					"id":98,
					"name":"Владыкино",
					"latitude":55.848193889977,
					"longitude":37.590496076721,
					"operationTime": "C 10-00 до 200-00"
				},
				{
					"id":99,
					"name":"Водный стадион",
					"latitude":55.840625832591,
					"longitude":37.48620830423,
					"operationTime": "C 10-00 до 200-00"
				},
				{
					"id":100,
					"name":"Войковская",
					"latitude":55.818004626573,
					"longitude":37.498112865082,
					"operationTime": "C 10-00 до 200-00"
				},
				{
					"id":101,
					"name":"Волгоградский проспект",
					"latitude":55.725584490948,
					"longitude":37.685235182526,
					"operationTime": "C 10-00 до 200-00"
				},
				{
					"id":122,
					"name":"Волжская",
					"latitude":55.690755094381,
					"longitude":37.755117901589,
					"operationTime": "C 10-00 до 200-00"
				},
				{
					"id":125,
					"name":"Волоколамская",
					"latitude":55.834608633462,
					"longitude":37.383139570114,
					"operationTime": "C 10-00 до 200-00"
				},
				{
					"id":128,
					"name":"Воробьевы горы",
					"latitude":55.709057275949,
					"longitude":37.557616957928,
					"operationTime": "C 10-00 до 200-00"
				},
				{
					"id":131,
					"name":"Выставочная",
					"latitude":55.750122137188,
					"longitude":37.542538702377,
					"operationTime": "C 10-00 до 200-00"
				},
				{
					"id":134,
					"name":"Выхино",
					"latitude":55.715863971218,
					"longitude":37.817174566132,
					"operationTime": "C 10-00 до 200-00"
				},
				{
					"id":138,
					"name":"Деловой центр",
					"latitude":55.749023816152,
					"longitude":37.53760648938
				},
				{
					"id":143,
					"name":"Динамо",
					"latitude":55.789041067244,
					"longitude":37.559795449155
				},
				{
					"id":145,
					"name":"Дмитровская",
					"latitude":55.807862150643,
					"longitude":37.580520363754
				},
				{
					"id":150,
					"name":"Добрынинская",
					"latitude":55.728951233249,
					"longitude":37.622731957672
				},
				{
					"id":155,
					"name":"Домодедовская",
					"latitude":55.610053054159,
					"longitude":37.717154481476
				},
				{
					"id":158,
					"name":"Достоевская",
					"latitude":55.781232857915,
					"longitude":37.614162964943
				},
				{
					"id":161,
					"name":"Дубровка",
					"latitude":55.717755358651,
					"longitude":37.6762595
				},
				{
					"id":166,
					"name":"Жулебино",
					"latitude":55.683998815827,
					"longitude":37.85542290741
				},
				{
					"id":168,
					"name":"Зябликово",
					"latitude":55.61333915512,
					"longitude":37.744132116394
				},
				{
					"id":169,
					"name":"Измайловская",
					"latitude":55.787709505554,
					"longitude":37.77966388623
				},
				{
					"id":171,
					"name":"Калужская",
					"latitude":55.656183890235,
					"longitude":37.540031584656
				},
				{
					"id":174,
					"name":"Кантемировская",
					"latitude":55.634711414586,
					"longitude":37.656968518524
				},
				{
					"id":181,
					"name":"Каховская",
					"latitude":55.652909863625,
					"longitude":37.600141232819
				},
				{
					"id":182,
					"name":"Каширская",
					"latitude":55.655663452659,
					"longitude":37.649642164032
				},
				{
					"id":188,
					"name":"Киевская",
					"latitude":55.744082356076,
					"longitude":37.566826667984
				},
				{
					"id":193,
					"name":"Китай-город",
					"latitude":55.756751881423,
					"longitude":37.631068007935
				},
				{
					"id":196,
					"name":"Кожуховская",
					"latitude":55.706247082149,
					"longitude":37.685484194443
				},
				{
					"id":200,
					"name":"Коломенская",
					"latitude":55.677556150778,
					"longitude":37.664566078049
				},
				{
					"id":203,
					"name":"Комсомольская",
					"latitude":55.775732248346,
					"longitude":37.656037502655
				},
				{
					"id":204,
					"name":"Коньково",
					"latitude":55.634005292216,
					"longitude":37.519906482803
				},
				{
					"id":207,
					"name":"Красногвардейская",
					"latitude":55.613620120095,
					"longitude":37.746418873016
				},
				{
					"id":211,
					"name":"Краснопресненская",
					"latitude":55.760210777149,
					"longitude":37.577135898148
				},
				{
					"id":212,
					"name":"Красносельская",
					"latitude":55.779975753015,
					"longitude":37.666077864418
				},
				{
					"id":213,
					"name":"Красные ворота",
					"latitude":55.768270128107,
					"longitude":37.647943362427
				},
				{
					"id":217,
					"name":"Крестьянская застава",
					"latitude":55.73231798429,
					"longitude":37.665559976196
				},
				{
					"id":221,
					"name":"Кропоткинская",
					"latitude":55.744939635218,
					"longitude":37.601566038345
				},
				{
					"id":223,
					"name":"Крылатское",
					"latitude":55.757907074183,
					"longitude":37.407367023804
				},
				{
					"id":226,
					"name":"Кузнецкий мост",
					"latitude":55.761568530527,
					"longitude":37.623768771164
				},
				{
					"id":229,
					"name":"Кузьминки",
					"latitude":55.705283499543,
					"longitude":37.763917665329
				},
				{
					"id":232,
					"name":"Кунцевская",
					"latitude":55.730610395554,
					"longitude":37.4468745
				},
				{
					"id":236,
					"name":"Курская",
					"latitude":55.758631874736,
					"longitude":37.659139514542
				},
				{
					"id":239,
					"name":"Кутузовская",
					"latitude":55.740564645669,
					"longitude":37.533988736771
				},
				{
					"id":242,
					"name":"Ленинский проспект",
					"latitude":55.708404081905,
					"longitude":37.587451858475
				},
				{
					"id":241,
					"name":"Лермонтовский проспект",
					"latitude":55.700189498194,
					"longitude":37.853026518524
				},
				{
					"id":243,
					"name":"Лесопарковая",
					"latitude":55.581627948645,
					"longitude":37.577910314819
				},
				{
					"id":89,
					"name":"Лиговский Проспект",
					"latitude":59.920717326113,
					"longitude":30.355128313492
				},
				{
					"id":244,
					"name":"Лубянка",
					"latitude":55.759125978954,
					"longitude":37.627356728836
				},
				{
					"id":245,
					"name":"Люблино",
					"latitude":55.677041284246,
					"longitude":37.762014228836
				},
				{
					"id":227,
					"name":"Марксистская",
					"latitude":55.741150642834,
					"longitude":37.656629838623
				},
				{
					"id":228,
					"name":"Марьина роща",
					"latitude":55.793523313969,
					"longitude":37.616630611114
				},
				{
					"id":230,
					"name":"Марьино",
					"latitude":55.649100337565,
					"longitude":37.744568611114
				},
				{
					"id":231,
					"name":"Маяковская",
					"latitude":55.769529566018,
					"longitude":37.597168824081
				},
				{
					"id":233,
					"name":"Медведково",
					"latitude":55.888027505116,
					"longitude":37.661590873016
				},
				{
					"id":234,
					"name":"Международная",
					"latitude":55.748749201242,
					"longitude":37.532922482803
				},
				{
					"id":235,
					"name":"Менделеевская",
					"latitude":55.781992846626,
					"longitude":37.599249484131
				},
				{
					"id":237,
					"name":"Митино",
					"latitude":55.846701387543,
					"longitude":37.361263415344
				},
				{
					"id":238,
					"name":"Молодёжная",
					"latitude":55.741318007701,
					"longitude":37.41567739682
				},
				{
					"id":240,
					"name":"Мякинино",
					"latitude":55.824980758848,
					"longitude":37.386206121704
				},
				{
					"id":214,
					"name":"Нагатинская",
					"latitude":55.683918235054,
					"longitude":37.622846423279
				},
				{
					"id":215,
					"name":"Нагорная",
					"latitude":55.672659756476,
					"longitude":37.610938619049
				},
				{
					"id":218,
					"name":"Нахимовский Проспект",
					"latitude":55.663483550769,
					"longitude":37.607034029114
				},
				{
					"id":219,
					"name":"Новогиреево",
					"latitude":55.752115437389,
					"longitude":37.8150629021
				},
				{
					"id":216,
					"name":"Новокосино",
					"latitude":55.744484375268,
					"longitude":37.866348470917
				},
				{
					"id":220,
					"name":"Новокузнецкая",
					"latitude":55.742378166823,
					"longitude":37.629328347885
				},
				{
					"id":222,
					"name":"Новослободская",
					"latitude":55.77946803258,
					"longitude":37.601248838623
				},
				{
					"id":224,
					"name":"Новоясеневская",
					"latitude":55.60183377778,
					"longitude":37.553098177246
				},
				{
					"id":225,
					"name":"Новые Черёмушки",
					"latitude":55.671119698638,
					"longitude":37.555222060852
				},
				{
					"id":205,
					"name":"Октябрьская",
					"latitude":55.729198845389,
					"longitude":37.611393208984
				},
				{
					"id":206,
					"name":"Октябрьское поле",
					"latitude":55.794197794991,
					"longitude":37.492427006607
				},
				{
					"id":208,
					"name":"Орехово",
					"latitude":55.612338070893,
					"longitude":37.696136179901
				},
				{
					"id":209,
					"name":"Отрадное",
					"latitude":55.864168118386,
					"longitude":37.605337026459
				},
				{
					"id":210,
					"name":"Охотный ряд",
					"latitude":55.75648697646,
					"longitude":37.61527285582
				},
				{
					"id":175,
					"name":"Павелецкая",
					"latitude":55.73142730498,
					"longitude":37.636211482803
				},
				{
					"id":176,
					"name":"Парк Культуры",
					"latitude":55.736071723957,
					"longitude":37.594985398148
				},
				{
					"id":177,
					"name":"Парк Победы",
					"latitude":55.735824791711,
					"longitude":37.517431484131
				},
				{
					"id":178,
					"name":"Партизанская",
					"latitude":55.788435867371,
					"longitude":37.749608822754
				},
				{
					"id":179,
					"name":"Первомайская",
					"latitude":55.793644419811,
					"longitude":37.799128465607
				},
				{
					"id":180,
					"name":"Перово",
					"latitude":55.751102443284,
					"longitude":37.784826563477
				},
				{
					"id":183,
					"name":"Петровско-Разумовская",
					"latitude":55.836566540428,
					"longitude":37.575494126984
				},
				{
					"id":184,
					"name":"Печатники",
					"latitude":55.692814716831,
					"longitude":37.728268753967
				},
				{
					"id":185,
					"name":"Пионерская",
					"latitude":55.736058917025,
					"longitude":37.467656857147
				},
				{
					"id":186,
					"name":"Планерная",
					"latitude":55.859551772119,
					"longitude":37.436897484131
				},
				{
					"id":187,
					"name":"Площадь Ильича",
					"latitude":55.747122276291,
					"longitude":37.680489820537
				},
				{
					"id":189,
					"name":"Площадь Революции",
					"latitude":55.75676837733,
					"longitude":37.62271985582
				},
				{
					"id":190,
					"name":"Полежаевская",
					"latitude":55.777430558378,
					"longitude":37.517080108459
				},
				{
					"id":191,
					"name":"Полянка",
					"latitude":55.736819383697,
					"longitude":37.618674347885
				},
				{
					"id":192,
					"name":"Пражская",
					"latitude":55.61116383353,
					"longitude":37.604314822754
				},
				{
					"id":194,
					"name":"Преображенская площадь",
					"latitude":55.796843692232,
					"longitude":37.716781029114
				},
				{
					"id":195,
					"name":"Пролетарская",
					"latitude":55.731219359566,
					"longitude":37.664770732788
				},
				{
					"id":197,
					"name":"Проспект Вернадского",
					"latitude":55.676533899894,
					"longitude":37.504628870361
				},
				{
					"id":198,
					"name":"Проспект Мира",
					"latitude":55.78173309233,
					"longitude":37.633245465607
				},
				{
					"id":199,
					"name":"Профсоюзная",
					"latitude":55.678756430957,
					"longitude":37.563335789688
				},
				{
					"id":201,
					"name":"Пушкинская",
					"latitude":55.765988223543,
					"longitude":37.604457899475
				},
				{
					"id":202,
					"name":"Пятницкое шоссе",
					"latitude":55.855088583627,
					"longitude":37.3540245
				},
				{
					"id":167,
					"name":"Речной вокзал",
					"latitude":55.854202805461,
					"longitude":37.476767941803
				},
				{
					"id":170,
					"name":"Рижская",
					"latitude":55.792446787423,
					"longitude":37.636143957672
				},
				{
					"id":172,
					"name":"Римская",
					"latitude":55.746445638532,
					"longitude":37.681392974869
				},
				{
					"id":173,
					"name":"Рязанский проспект",
					"latitude":55.717794709947,
					"longitude":37.793928365082
				},
				{
					"id":146,
					"name":"Савёловская",
					"latitude":55.793989742021,
					"longitude":37.587266531738
				},
				{
					"id":147,
					"name":"Свиблово",
					"latitude":55.854664634058,
					"longitude":37.651233732788
				},
				{
					"id":148,
					"name":"Севастопольская",
					"latitude":55.651503245879,
					"longitude":37.598159194443
				},
				{
					"id":149,
					"name":"Семёновская",
					"latitude":55.783086449657,
					"longitude":37.719402042328
				},
				{
					"id":151,
					"name":"Серпуховская",
					"latitude":55.726770598634,
					"longitude":37.624748388885
				},
				{
					"id":152,
					"name":"Славянский Бульвар",
					"latitude":55.730905423104,
					"longitude":37.472707441803
				},
				{
					"id":153,
					"name":"Смоленская",
					"latitude":55.748975559226,
					"longitude":37.581990093918
				},
				{
					"id":154,
					"name":"Сокол",
					"latitude":55.805574018148,
					"longitude":37.515281026459
				},
				{
					"id":156,
					"name":"Сокольники",
					"latitude":55.78923454716,
					"longitude":37.679602940475
				},
				{
					"id":157,
					"name":"Спартак",
					"latitude":55.819166238227,
					"longitude":37.435466687836
				},
				{
					"id":159,
					"name":"Спортивная",
					"latitude":55.722361120602,
					"longitude":37.561970007935
				},
				{
					"id":160,
					"name":"Сретенский Бульвар",
					"latitude":55.765832532717,
					"longitude":37.637350824081
				},
				{
					"id":162,
					"name":"Строгино",
					"latitude":55.803655520391,
					"longitude":37.405284724884
				},
				{
					"id":163,
					"name":"Студенческая",
					"latitude":55.738814041669,
					"longitude":37.548300398148
				},
				{
					"id":164,
					"name":"Сухаревская",
					"latitude":55.772248252889,
					"longitude":37.632106194443
				},
				{
					"id":165,
					"name":"Сходненская",
					"latitude":55.851426656802,
					"longitude":37.438820904755
				},
				{
					"id":129,
					"name":"Таганская",
					"latitude":55.742311730805,
					"longitude":37.653574653442
				},
				{
					"id":130,
					"name":"Тверская",
					"latitude":55.764298005938,
					"longitude":37.605596177246
				},
				{
					"id":132,
					"name":"Театральная",
					"latitude":55.758783078148,
					"longitude":37.617744873016
				},
				{
					"id":133,
					"name":"Текстильщики",
					"latitude":55.708955587177,
					"longitude":37.73329160318
				},
				{
					"id":135,
					"name":"Тёплый Стан",
					"latitude":55.619634930417,
					"longitude":37.506254822754
				},
				{
					"id":136,
					"name":"Тимирязевская",
					"latitude":55.818831524804,
					"longitude":37.574430812134
				},
				{
					"id":137,
					"name":"Третьяковская",
					"latitude":55.740604757543,
					"longitude":37.625691888885
				},
				{
					"id":139,
					"name":"Тропарёво",
					"latitude":55.644384934255,
					"longitude":37.472491703705
				},
				{
					"id":140,
					"name":"Трубная",
					"latitude":55.767618713981,
					"longitude":37.6219025
				},
				{
					"id":141,
					"name":"Тульская",
					"latitude":55.70955506077,
					"longitude":37.622632957672
				},
				{
					"id":142,
					"name":"Тургеневская",
					"latitude":55.765251082126,
					"longitude":37.636860517197
				},
				{
					"id":144,
					"name":"Тушинская",
					"latitude":55.82559412499,
					"longitude":37.435972716919
				},
				{
					"id":120,
					"name":"Улица 1905 года",
					"latitude":55.763963232725,
					"longitude":37.562233891541
				},
				{
					"id":124,
					"name":"Улица академика Янгеля",
					"latitude":55.595815951486,
					"longitude":37.600170744705
				},
				{
					"id":121,
					"name":"Улица Горчакова",
					"latitude":55.542135536384,
					"longitude":37.532245739426
				},
				{
					"id":127,
					"name":"Улица Скобелевская",
					"latitude":55.547717483871,
					"longitude":37.553395412689
				},
				{
					"id":126,
					"name":"Улица Старокачаловская",
					"latitude":55.568096093546,
					"longitude":37.576718728836
				},
				{
					"id":123,
					"name":"Университет",
					"latitude":55.691779221426,
					"longitude":37.534757805557
				},
				{
					"id":118,
					"name":"Филевский Парк",
					"latitude":55.739664043368,
					"longitude":37.483907857147
				},
				{
					"id":119,
					"name":"Фили",
					"latitude":55.746768601298,
					"longitude":37.514025820099
				},
				{
					"id":117,
					"name":"Фрунзенская",
					"latitude":55.727395753307,
					"longitude":37.58073619577
				},
				{
					"id":115,
					"name":"Царицыно",
					"latitude":55.620432828917,
					"longitude":37.670024560188
				},
				{
					"id":116,
					"name":"Цветной Бульвар",
					"latitude":55.771639968197,
					"longitude":37.620621219574
				},
				{
					"id":110,
					"name":"Черкизовская",
					"latitude":55.802746561294,
					"longitude":37.744904330688
				},
				{
					"id":111,
					"name":"Чертановская",
					"latitude":55.640999456006,
					"longitude":37.604798997345
				},
				{
					"id":112,
					"name":"Чеховская",
					"latitude":55.765679462944,
					"longitude":37.608478136246
				},
				{
					"id":113,
					"name":"Чистые Пруды",
					"latitude":55.76491525349,
					"longitude":37.63838209259
				},
				{
					"id":114,
					"name":"Чкаловская",
					"latitude":55.756075481886,
					"longitude":37.659714111114
				},
				{
					"id":107,
					"name":"Шаболовская",
					"latitude":55.71876627339,
					"longitude":37.608163280426
				},
				{
					"id":108,
					"name":"Шипиловская",
					"latitude":55.622075080959,
					"longitude":37.742574514542
				},
				{
					"id":109,
					"name":"Шоссе Энтузиастов",
					"latitude":55.758424672502,
					"longitude":37.751443525131
				},
				{
					"id":106,
					"name":"Щёлковская",
					"latitude":55.810034440573,
					"longitude":37.798309236771
				},
				{
					"id":105,
					"name":"Электрозаводская",
					"latitude":55.782090461612,
					"longitude":37.705267406746
				},
				{
					"id":103,
					"name":"Юго-Западная",
					"latitude":55.662843043614,
					"longitude":37.482113439148
				},
				{
					"id":104,
					"name":"Южная",
					"latitude":55.622787893484,
					"longitude":37.609777060852
				},
				{
					"id":102,
					"name":"Ясенево",
					"latitude":55.606054233777,
					"longitude":37.535267317474
				}
			]
		},
		{
			"id":2,
			"name":"Санкт-Петербург",
			"metro":[
				{
					"id":48,
					"name":"Автово",
					"latitude":59.867243517397,
					"longitude":30.261317669311
				},
				{
					"id":73,
					"name":"Адмиралтейская",
					"latitude":59.935878025685,
					"longitude":30.315155398148
				},
				{
					"id":64,
					"name":"Академическая",
					"latitude":55.75485218641,
					"longitude":37.618168761866
				},
				{
					"id":66,
					"name":"Академическая",
					"latitude":60.012718900577,
					"longitude":30.396164330689
				},
				{
					"id":51,
					"name":"Балтийская",
					"latitude":59.907105649324,
					"longitude":30.299477669311
				},
				{
					"id":76,
					"name":"Бухарестская",
					"latitude":59.883682979865,
					"longitude":30.369060246033
				},
				{
					"id":90,
					"name":"Василеостровская",
					"latitude":59.942494226583,
					"longitude":30.278230584656
				},
				{
					"id":54,
					"name":"Владимирская",
					"latitude":59.927466450613,
					"longitude":30.348150042328
				},
				{
					"id":75,
					"name":"Волковская",
					"latitude":59.895928134836,
					"longitude":30.357961626984
				},
				{
					"id":60,
					"name":"Выборгская",
					"latitude":59.971002244955,
					"longitude":30.347313313492
				},
				{
					"id":32,
					"name":"Горьковская",
					"latitude":59.95614768687,
					"longitude":30.318838042328
				},
				{
					"id":37,
					"name":"Гостиный Двор",
					"latitude":59.933901452577,
					"longitude":30.333765957672
				},
				{
					"id":65,
					"name":"Гражданский Проспект",
					"latitude":60.034914757336,
					"longitude":30.41822235582
				},
				{
					"id":67,
					"name":"Девяткино",
					"latitude":60.050521267909,
					"longitude":30.443874968262
				},
				{
					"id":55,
					"name":"Достоевская",
					"latitude":59.928169102446,
					"longitude":30.346161584656
				},
				{
					"id":86,
					"name":"Елизаровская",
					"latitude":59.896616306616,
					"longitude":30.423752042328
				},
				{
					"id":44,
					"name":"Звёздная",
					"latitude":59.8331370597,
					"longitude":30.349374126984
				},
				{
					"id":53,
					"name":"Звенигородская",
					"latitude":59.922266099625,
					"longitude":30.335566626984
				},
				{
					"id":49,
					"name":"Кировский Завод",
					"latitude":59.879632365168,
					"longitude":30.261896126984
				},
				{
					"id":68,
					"name":"Комендантский Проспект",
					"latitude":60.008447048473,
					"longitude":30.258277023804
				},
				{
					"id":70,
					"name":"Крестовский Остров",
					"latitude":59.971788379631,
					"longitude":30.259501746033
				},
				{
					"id":45,
					"name":"Купчино",
					"latitude":59.830267562716,
					"longitude":30.376918875671
				},
				{
					"id":93,
					"name":"Ладожская",
					"latitude":59.932462951219,
					"longitude":30.4393055
				},
				{
					"id":47,
					"name":"Ленинский Проспект",
					"latitude":59.851623125303,
					"longitude":30.269651587311
				},
				{
					"id":61,
					"name":"Лесная",
					"latitude":59.98472274634,
					"longitude":30.344311957672
				},
				{
					"id":85,
					"name":"Ломоносовская",
					"latitude":59.877221397489,
					"longitude":30.441779313492
				},
				{
					"id":56,
					"name":"Маяковская",
					"latitude":59.931426757892,
					"longitude":30.35512485582
				},
				{
					"id":77,
					"name":"Международная",
					"latitude":59.870192969061,
					"longitude":30.37923585582
				},
				{
					"id":43,
					"name":"Московская",
					"latitude":59.849077384372,
					"longitude":30.321997484131
				},
				{
					"id":40,
					"name":"Московские Ворота",
					"latitude":59.891461411296,
					"longitude":30.318056330688
				},
				{
					"id":50,
					"name":"Нарвская",
					"latitude":59.901100978945,
					"longitude":30.274853296295
				},
				{
					"id":33,
					"name":"Невский Проспект",
					"latitude":59.935341382138,
					"longitude":30.327193703705
				},
				{
					"id":92,
					"name":"Новочеркасская",
					"latitude":59.929501176437,
					"longitude":30.41218040741
				},
				{
					"id":74,
					"name":"Обводный Канал",
					"latitude":59.914604807512,
					"longitude":30.349549669312
				},
				{
					"id":83,
					"name":"Обухово",
					"latitude":59.848604462122,
					"longitude":30.457681753967
				},
				{
					"id":27,
					"name":"Озерки",
					"latitude":60.037151022561,
					"longitude":30.321748398147
				},
				{
					"id":42,
					"name":"Парк Победы",
					"latitude":59.866226096345,
					"longitude":30.321800669311
				},
				{
					"id":25,
					"name":"Парнас",
					"latitude":60.066972307025,
					"longitude":30.333994415344
				},
				{
					"id":31,
					"name":"Петроградская",
					"latitude":59.966309495161,
					"longitude":30.310851142853
				},
				{
					"id":29,
					"name":"Пионерская",
					"latitude":60.002517257564,
					"longitude":30.296598126984
				},
				{
					"id":88,
					"name":"Площадь Александра Невского",
					"latitude":59.923538812788,
					"longitude":30.38347119046
				},
				{
					"id":57,
					"name":"Площадь Восстания",
					"latitude":59.931528027182,
					"longitude":30.360452211639
				},
				{
					"id":58,
					"name":"Площадь Ленина",
					"latitude":59.955702615748,
					"longitude":30.355771923279
				},
				{
					"id":62,
					"name":"Площадь Мужества",
					"latitude":59.999626136986,
					"longitude":30.366400584656
				},
				{
					"id":63,
					"name":"Политехническая",
					"latitude":60.00887594351,
					"longitude":30.37091667791
				},
				{
					"id":91,
					"name":"Приморская",
					"latitude":59.94843423039,
					"longitude":30.234569126984
				},
				{
					"id":84,
					"name":"Пролетарская",
					"latitude":59.865121258268,
					"longitude":30.47026185582
				},
				{
					"id":94,
					"name":"Проспект Большевиков",
					"latitude":59.919847325396,
					"longitude":30.466781542328
				},
				{
					"id":46,
					"name":"Проспект Ветеранов",
					"latitude":59.841786306604,
					"longitude":30.250523126984
				},
				{
					"id":26,
					"name":"Проспект Просвещения",
					"latitude":60.051489717575,
					"longitude":30.33245085582
				},
				{
					"id":52,
					"name":"Пушкинская",
					"latitude":59.920629917197,
					"longitude":30.32980985582
				},
				{
					"id":82,
					"name":"Рыбацкое",
					"latitude":59.831390958288,
					"longitude":30.502377919327
				},
				{
					"id":35,
					"name":"Садовая",
					"latitude":59.927170471849,
					"longitude":30.317611685181
				},
				{
					"id":36,
					"name":"Сенная Площадь",
					"latitude":59.926972257908,
					"longitude":30.32040485582
				},
				{
					"id":34,
					"name":"Спасская",
					"latitude":59.926575257904,
					"longitude":30.319956517197
				},
				{
					"id":72,
					"name":"Спортивная",
					"latitude":59.952161846651,
					"longitude":30.291527078049
				},
				{
					"id":69,
					"name":"Старая Деревня",
					"latitude":59.989353503849,
					"longitude":30.25510621628
				},
				{
					"id":38,
					"name":"Технологический Институт",
					"latitude":59.916232548741,
					"longitude":30.318426533066
				},
				{
					"id":28,
					"name":"Удельная",
					"latitude":60.016678291586,
					"longitude":30.315843084656
				},
				{
					"id":95,
					"name":"Улица Дыбенко",
					"latitude":59.907448035151,
					"longitude":30.483230253967
				},
				{
					"id":39,
					"name":"Фрунзенская",
					"latitude":59.906135148112,
					"longitude":30.317497813492
				},
				{
					"id":30,
					"name":"Чёрная Речка",
					"latitude":59.985474881815,
					"longitude":30.300907686508
				},
				{
					"id":59,
					"name":"Чернышевская",
					"latitude":59.944427601292,
					"longitude":30.359911126984
				},
				{
					"id":71,
					"name":"Чкаловская",
					"latitude":59.960977647866,
					"longitude":30.291937
				},
				{
					"id":41,
					"name":"Электросила",
					"latitude":59.87908548905,
					"longitude":30.3187065
				}
			]
		},
		{
			"id":3,
			"name":"Екатеринбург",
			"metro":[
				{
					"id":254,
					"name":"Ботаническая",
					"latitude":56.796815150794,
					"longitude":60.631817547607
				},
				{
					"id":252,
					"name":"Геологическая",
					"latitude":56.826855949521,
					"longitude":60.602165632263
				},
				{
					"id":250,
					"name":"Динамо",
					"latitude":56.847771240296,
					"longitude":60.599319669312
				},
				{
					"id":248,
					"name":"Машиностроителей",
					"latitude":56.878499149978,
					"longitude":60.612136584656
				},
				{
					"id":251,
					"name":"Площадь 1905 года",
					"latitude":56.835961681143,
					"longitude":60.598858947082
				},
				{
					"id":246,
					"name":"Проспект Космонавтов",
					"latitude":56.901179444979,
					"longitude":60.613813126984
				},
				{
					"id":247,
					"name":"Уралмаш",
					"latitude":56.887768236542,
					"longitude":60.613092616394
				},
				{
					"id":249,
					"name":"Уральская",
					"latitude":56.857703125022,
					"longitude":60.600151312164
				},
				{
					"id":253,
					"name":"Чкаловская",
					"latitude":56.808406262296,
					"longitude":60.610835246033
				}
			]
		},
		{
			"id":4,
			"name":"Казань",
			"metro":[
				{
					"id":255,
					"name":"Авиастроительная",
					"latitude":55.856442166342,
					"longitude":49.084259465607
				},
				{
					"id":262,
					"name":"Аметьево",
					"latitude":55.764564395563,
					"longitude":49.168347859802
				},
				{
					"id":263,
					"name":"Горки",
					"latitude":55.759683193856,
					"longitude":49.191466261902
				},
				{
					"id":258,
					"name":"Козья слобода",
					"latitude":55.817285057992,
					"longitude":49.097494685181
				},
				{
					"id":259,
					"name":"Кремлевская",
					"latitude":55.795923945765,
					"longitude":49.106536042328
				},
				{
					"id":260,
					"name":"Площадь Габдуллы Тукая",
					"latitude":55.78682523647,
					"longitude":49.122340076721
				},
				{
					"id":264,
					"name":"Проспект Победы",
					"latitude":55.749355545127,
					"longitude":49.208639253967
				},
				{
					"id":256,
					"name":"Северный вокзал",
					"latitude":55.841155779046,
					"longitude":49.081053362427
				},
				{
					"id":261,
					"name":"Суконная слобода",
					"latitude":55.776368641088,
					"longitude":49.143476129639
				},
				{
					"id":257,
					"name":"Яшьлек",
					"latitude":55.829002747691,
					"longitude":49.082218854492
				}
			]
		},
		{
			"id":5,
			"name":"Нижний Новгород",
			"metro":[
				{
					"id":272,
					"name":"Автозаводская",
					"latitude":56.257936070206,
					"longitude":43.902605941803
				},
				{
					"id":278,
					"name":"Буревестник",
					"latitude":56.33352671281,
					"longitude":43.894065167984
				},
				{
					"id":277,
					"name":"Бурнаковская",
					"latitude":56.325501595067,
					"longitude":43.913291248688
				},
				{
					"id":265,
					"name":"Горьковская",
					"latitude":56.313445361802,
					"longitude":43.993575481476
				},
				{
					"id":270,
					"name":"Двигатель Революции",
					"latitude":56.275881383205,
					"longitude":43.920330650787
				},
				{
					"id":269,
					"name":"Заречная",
					"latitude":56.284630065393,
					"longitude":43.926712108459
				},
				{
					"id":276,
					"name":"Канавинская",
					"latitude":56.320618036094,
					"longitude":43.926619126984
				},
				{
					"id":274,
					"name":"Кировская",
					"latitude":56.246708957554,
					"longitude":43.875130632263
				},
				{
					"id":273,
					"name":"Комсомольская",
					"latitude":56.252172518544,
					"longitude":43.889073108459
				},
				{
					"id":268,
					"name":"Ленинская",
					"latitude":56.29805908588,
					"longitude":43.937882042328
				},
				{
					"id":266,
					"name":"Московская",
					"latitude":56.322024121612,
					"longitude":43.948345383606
				},
				{
					"id":275,
					"name":"Парк культуры",
					"latitude":56.241752509281,
					"longitude":43.859489875671
				},
				{
					"id":271,
					"name":"Пролетарская",
					"latitude":56.266967966267,
					"longitude":43.914529875671
				},
				{
					"id":267,
					"name":"Чкаловская",
					"latitude":56.309778518688,
					"longitude":43.937318738098
				}
			]
		},
		{
			"id":6,
			"name":"Новосибирск",
			"metro":[
				{
					"id":290,
					"name":"Берёзовая роща",
					"latitude":55.043401459696,
					"longitude":82.951603582001
				},
				{
					"id":280,
					"name":"Гагаринская",
					"latitude":55.051933609459,
					"longitude":82.914083854492
				},
				{
					"id":279,
					"name":"Заельцовская",
					"latitude":55.058559928851,
					"longitude":82.913325349213
				},
				{
					"id":291,
					"name":"Золотая Нива",
					"latitude":55.037324439178,
					"longitude":82.976774060852
				},
				{
					"id":281,
					"name":"Красный проспект",
					"latitude":55.041797362013,
					"longitude":82.916741481476
				},
				{
					"id":289,
					"name":"Маршала Покрышкина",
					"latitude":55.044113812618,
					"longitude":82.93698270636
				},
				{
					"id":283,
					"name":"Октябрьская",
					"latitude":55.018345594471,
					"longitude":82.939971739426
				},
				{
					"id":287,
					"name":"Площадь Гарина-Михайловского",
					"latitude":55.036061740734,
					"longitude":82.899808383606
				},
				{
					"id":282,
					"name":"Площадь Ленина",
					"latitude":55.030550232497,
					"longitude":82.919051378296
				},
				{
					"id":286,
					"name":"Площадь Маркса",
					"latitude":54.982587092502,
					"longitude":82.891675945755
				},
				{
					"id":284,
					"name":"Речной вокзал",
					"latitude":55.009360224474,
					"longitude":82.938804145508
				},
				{
					"id":288,
					"name":"Сибирская",
					"latitude":55.042820868549,
					"longitude":82.92044929895
				},
				{
					"id":285,
					"name":"Студенческая",
					"latitude":54.989732012092,
					"longitude":82.907851129639
				}
			]
		},
		{
			"id":7,
			"name":"Самара",
			"metro":[
				{
					"id":292,
					"name":"Алабинская",
					"latitude":53.209604388813,
					"longitude":50.134909944458
				},
				{
					"id":299,
					"name":"Безымянка",
					"latitude":53.21211509452,
					"longitude":50.247681108459
				},
				{
					"id":295,
					"name":"Гагаринская",
					"latitude":53.200109900697,
					"longitude":50.177599552917
				},
				{
					"id":300,
					"name":"Кировская",
					"latitude":53.21143012445,
					"longitude":50.26812800528
				},
				{
					"id":294,
					"name":"Московская",
					"latitude":53.202997414097,
					"longitude":50.160784002655
				},
				{
					"id":298,
					"name":"Победа",
					"latitude":53.206607097024,
					"longitude":50.235756177246
				},
				{
					"id":293,
					"name":"Российская",
					"latitude":53.211012235002,
					"longitude":50.150436449738
				},
				{
					"id":297,
					"name":"Советская",
					"latitude":53.201417790497,
					"longitude":50.221959502655
				},
				{
					"id":296,
					"name":"Спортивная",
					"latitude":53.200745018935,
					"longitude":50.200116383606
				},
				{
					"id":301,
					"name":"Юнгородок",
					"latitude":53.212797047165,
					"longitude":50.283442560852
				}
			]
		},
		{
			"id":824,
			"name":"Архангельск "
		},
		{
			"id":825,
			"name":"Архипо-Осиповка"
		},
		{
			"id":826,
			"name":"Асбест"
		},
		{
			"id":827,
			"name":"Астана"
		},
		{
			"id":828,
			"name":"Астрахань"
		},
		{
			"id":829,
			"name":"Атырау"
		},
		{
			"id":830,
			"name":"Ачинск"
		},
		{
			"id":831,
			"name":"Аша"
		},
		{
			"id":832,
			"name":"Байкалово"
		},
		{
			"id":833,
			"name":"Бакал"
		},
		{
			"id":834,
			"name":"Баклаши"
		},
		{
			"id":835,
			"name":"Баковка"
		},
		{
			"id":836,
			"name":"Балабаново"
		},
		{
			"id":837,
			"name":"Балаково"
		},
		{
			"id":838,
			"name":"Балахна"
		},
		{
			"id":839,
			"name":"Балашиха"
		},
		{
			"id":840,
			"name":"Баранчинский"
		},
		{
			"id":841,
			"name":"Барвиха"
		},
		{
			"id":842,
			"name":"Барнаул"
		},
		{
			"id":843,
			"name":"Белгород"
		},
		{
			"id":844,
			"name":"Белгород (Губкин)"
		},
		{
			"id":845,
			"name":"Белгород (Дубовое)"
		},
		{
			"id":846,
			"name":"Белгород (Красная Яруга)"
		},
		{
			"id":847,
			"name":"Белгород (Ст. Оскол)"
		},
		{
			"id":848,
			"name":"Белебей"
		},
		{
			"id":849,
			"name":"Белозерный"
		},
		{
			"id":850,
			"name":"Белорецк"
		},
		{
			"id":851,
			"name":"Белореченский"
		},
		{
			"id":852,
			"name":"Белоярский"
		},
		{
			"id":853,
			"name":"Березнецова"
		},
		{
			"id":854,
			"name":"Березник"
		},
		{
			"id":855,
			"name":"Березники"
		},
		{
			"id":856,
			"name":"Березовский"
		},
		{
			"id":857,
			"name":"Бийск"
		},
		{
			"id":858,
			"name":"Биробиджан"
		},
		{
			"id":859,
			"name":"Бирск"
		},
		{
			"id":860,
			"name":"Благовещенск"
		},
		{
			"id":861,
			"name":"Благодарный"
		},
		{
			"id":862,
			"name":"Бобровский"
		},
		{
			"id":863,
			"name":"Богданович "
		},
		{
			"id":864,
			"name":"Боголюбово"
		},
		{
			"id":865,
			"name":"Богородск"
		},
		{
			"id":866,
			"name":"Бологое"
		},
		{
			"id":867,
			"name":"Большие Вяземы"
		},
		{
			"id":868,
			"name":"Большой Камень"
		},
		{
			"id":869,
			"name":"Бор"
		},
		{
			"id":870,
			"name":"Борисоглебск"
		},
		{
			"id":871,
			"name":"Боровичи"
		},
		{
			"id":872,
			"name":"Боровск"
		},
		{
			"id":873,
			"name":"Братск"
		},
		{
			"id":874,
			"name":"Брехово"
		},
		{
			"id":875,
			"name":"Бронницы"
		},
		{
			"id":876,
			"name":"Брянск"
		},
		{
			"id":877,
			"name":"Бугульма"
		},
		{
			"id":878,
			"name":"Буденовск"
		},
		{
			"id":879,
			"name":"Буланаш "
		},
		{
			"id":880,
			"name":"Быково"
		},
		{
			"id":881,
			"name":"Ванино"
		},
		{
			"id":882,
			"name":"Великий Новгород"
		},
		{
			"id":883,
			"name":"Вельск"
		},
		{
			"id":884,
			"name":"Вербилки"
		},
		{
			"id":885,
			"name":"Верещагино"
		},
		{
			"id":886,
			"name":"Верхнеуральский"
		},
		{
			"id":887,
			"name":"Верхний тагил"
		},
		{
			"id":888,
			"name":"Верхний Уфалей"
		},
		{
			"id":889,
			"name":"Верхняя Пышма"
		},
		{
			"id":890,
			"name":"Верхняя Салда"
		},
		{
			"id":891,
			"name":"Верхняя Тойма"
		},
		{
			"id":892,
			"name":"Верхотурье"
		},
		{
			"id":893,
			"name":"Вешки"
		},
		{
			"id":894,
			"name":"Вешняково"
		},
		{
			"id":895,
			"name":"Видное"
		},
		{
			"id":896,
			"name":"Визинга"
		},
		{
			"id":897,
			"name":"Вилегода"
		},
		{
			"id":898,
			"name":"Вичуга"
		},
		{
			"id":899,
			"name":"Владивосток"
		},
		{
			"id":900,
			"name":"Владикавказ"
		},
		{
			"id":901,
			"name":"Владимир"
		},
		{
			"id":902,
			"name":"Власиха"
		},
		{
			"id":903,
			"name":"ВНИИССОК"
		},
		{
			"id":904,
			"name":"Внуковское"
		},
		{
			"id":905,
			"name":"Волгоград"
		},
		{
			"id":906,
			"name":"Волжский"
		},
		{
			"id":907,
			"name":"Вологда"
		},
		{
			"id":908,
			"name":"Волоколамск"
		},
		{
			"id":909,
			"name":"Волхов"
		},
		{
			"id":910,
			"name":"Волчанск"
		},
		{
			"id":911,
			"name":"Вольск"
		},
		{
			"id":912,
			"name":"Воронеж"
		},
		{
			"id":913,
			"name":"Воскресенск"
		},
		{
			"id":914,
			"name":"Воткинск"
		},
		{
			"id":915,
			"name":"Врангель"
		},
		{
			"id":916,
			"name":"Всеволожск"
		},
		{
			"id":917,
			"name":"Выборг"
		},
		{
			"id":918,
			"name":"Выльгорт"
		},
		{
			"id":919,
			"name":"Вышний Волочёк"
		},
		{
			"id":920,
			"name":"Вялки дер"
		},
		{
			"id":921,
			"name":"Вятские Поляны"
		},
		{
			"id":922,
			"name":"Гатчина"
		},
		{
			"id":923,
			"name":"Геленджик"
		},
		{
			"id":924,
			"name":"Глазов"
		},
		{
			"id":925,
			"name":"Глебовский"
		},
		{
			"id":926,
			"name":"Голицино"
		},
		{
			"id":927,
			"name":"Голицыно"
		},
		{
			"id":928,
			"name":"Горелово"
		},
		{
			"id":929,
			"name":"Горки-10"
		},
		{
			"id":930,
			"name":"Горки-11"
		},
		{
			"id":931,
			"name":"Горки-2"
		},
		{
			"id":932,
			"name":"Городище"
		},
		{
			"id":933,
			"name":"Горячий ключ"
		},
		{
			"id":934,
			"name":"Губаха"
		},
		{
			"id":935,
			"name":"Губкинский"
		},
		{
			"id":936,
			"name":"ГУВ МО Наро-Фоминского района СББЖ"
		},
		{
			"id":937,
			"name":"Гулькевичи"
		},
		{
			"id":938,
			"name":"Гусиноозерск"
		},
		{
			"id":939,
			"name":"Гусь-Хрустальный"
		},
		{
			"id":940,
			"name":"Давлеканово"
		},
		{
			"id":941,
			"name":"Двуреченск"
		},
		{
			"id":942,
			"name":"Деденево"
		},
		{
			"id":943,
			"name":"Дедовск"
		},
		{
			"id":944,
			"name":"ДЕУ"
		},
		{
			"id":945,
			"name":"Дзержинск"
		},
		{
			"id":946,
			"name":"Дзержинский"
		},
		{
			"id":947,
			"name":"Дивногорск"
		},
		{
			"id":948,
			"name":"Дивный"
		},
		{
			"id":949,
			"name":"Дмитров"
		},
		{
			"id":950,
			"name":"Добрянка"
		},
		{
			"id":951,
			"name":"Долгопрудный"
		},
		{
			"id":952,
			"name":"Долинск"
		},
		{
			"id":953,
			"name":"Домодедово"
		},
		{
			"id":954,
			"name":"Дорохово"
		},
		{
			"id":955,
			"name":"Дубки"
		},
		{
			"id":956,
			"name":"Дубна"
		},
		{
			"id":957,
			"name":"Дубовая Роща"
		},
		{
			"id":958,
			"name":"Дубровка"
		},
		{
			"id":959,
			"name":"Дурыкино"
		},
		{
			"id":960,
			"name":"Егоревск"
		},
		{
			"id":961,
			"name":"Егорьевск"
		},
		{
			"id":962,
			"name":"Ейск"
		},
		{
			"id":963,
			"name":"Екатернбург"
		},
		{
			"id":964,
			"name":"Елец"
		},
		{
			"id":965,
			"name":"Еманжелинск"
		},
		{
			"id":966,
			"name":"Ермолино"
		},
		{
			"id":967,
			"name":"Ессентуки"
		},
		{
			"id":968,
			"name":"Жаворонки"
		},
		{
			"id":969,
			"name":"Железногорск"
		},
		{
			"id":970,
			"name":"Железнодорожный"
		},
		{
			"id":971,
			"name":"Жуков (Протва)"
		},
		{
			"id":972,
			"name":"Жуковка"
		},
		{
			"id":973,
			"name":"Жуковский"
		},
		{
			"id":974,
			"name":"Жулебино"
		},
		{
			"id":975,
			"name":"Заводоуковск"
		},
		{
			"id":976,
			"name":"Заволжье"
		},
		{
			"id":977,
			"name":"Загорянский"
		},
		{
			"id":978,
			"name":"Запрудня"
		},
		{
			"id":979,
			"name":"Запруня"
		},
		{
			"id":980,
			"name":"Зарайск"
		},
		{
			"id":981,
			"name":"Заречный"
		},
		{
			"id":982,
			"name":"Заринск"
		},
		{
			"id":983,
			"name":"Звенигород"
		},
		{
			"id":984,
			"name":"Зверосовхоз"
		},
		{
			"id":985,
			"name":"Зеленая Роща"
		},
		{
			"id":986,
			"name":"Зеленогорск"
		},
		{
			"id":987,
			"name":"Зеленоград"
		},
		{
			"id":988,
			"name":"Зеленодольск"
		},
		{
			"id":989,
			"name":"Зеленокумск"
		},
		{
			"id":990,
			"name":"Златоуст"
		},
		{
			"id":991,
			"name":"Зубцов"
		},
		{
			"id":992,
			"name":"Иваново"
		},
		{
			"id":993,
			"name":"Ивантеевка"
		},
		{
			"id":994,
			"name":"Ивантеевка, "
		},
		{
			"id":995,
			"name":"Ивдель"
		},
		{
			"id":996,
			"name":"Иглино"
		},
		{
			"id":997,
			"name":"Игрим"
		},
		{
			"id":998,
			"name":"Ижевск"
		},
		{
			"id":999,
			"name":"Излучинск "
		},
		{
			"id":1000,
			"name":"Изобильный"
		},
		{
			"id":1001,
			"name":"Ильинский"
		},
		{
			"id":1002,
			"name":"Йошкар-Ола"
		},
		{
			"id":1003,
			"name":"Ирбит"
		},
		{
			"id":1004,
			"name":"Иркутск"
		},
		{
			"id":1005,
			"name":"Истра"
		},
		{
			"id":1006,
			"name":"Ишим"
		},
		{
			"id":1007,
			"name":"Ишимбай"
		},
		{
			"id":1008,
			"name":"Калининград"
		},
		{
			"id":1009,
			"name":"Калининец"
		},
		{
			"id":1010,
			"name":"Калининец"
		},
		{
			"id":1011,
			"name":"Калуга"
		},
		{
			"id":1012,
			"name":"Каменск-уральский"
		},
		{
			"id":1013,
			"name":"Камышлов "
		},
		{
			"id":1014,
			"name":"Канск"
		},
		{
			"id":1015,
			"name":"Караганда"
		},
		{
			"id":1016,
			"name":"Каргополь"
		},
		{
			"id":1017,
			"name":"Карпинск"
		},
		{
			"id":1018,
			"name":"Карпогоры"
		},
		{
			"id":1019,
			"name":"Карталы"
		},
		{
			"id":1020,
			"name":"Касимов"
		},
		{
			"id":1021,
			"name":"Каскелен"
		},
		{
			"id":1022,
			"name":"Касли"
		},
		{
			"id":1023,
			"name":"Качканар"
		},
		{
			"id":1024,
			"name":"Кашир"
		},
		{
			"id":1025,
			"name":"Кашира"
		},
		{
			"id":1026,
			"name":"Кашира 2"
		},
		{
			"id":1027,
			"name":"Кашира 3"
		},
		{
			"id":1028,
			"name":"Кашира 4"
		},
		{
			"id":1029,
			"name":"Кемерово"
		},
		{
			"id":1030,
			"name":"Кимры"
		},
		{
			"id":1031,
			"name":"Кингисепп"
		},
		{
			"id":1032,
			"name":"кинешма"
		},
		{
			"id":1033,
			"name":"Киржач"
		},
		{
			"id":1034,
			"name":"Киров"
		},
		{
			"id":1035,
			"name":"Кировград"
		},
		{
			"id":1036,
			"name":"Кирово-Чепецк"
		},
		{
			"id":1037,
			"name":"Кировск"
		},
		{
			"id":1038,
			"name":"Кирс"
		},
		{
			"id":1039,
			"name":"Кисловодск"
		},
		{
			"id":1040,
			"name":"Климовск"
		},
		{
			"id":1041,
			"name":"Клин"
		},
		{
			"id":1042,
			"name":"Ковров"
		},
		{
			"id":1043,
			"name":"Когалым"
		},
		{
			"id":1044,
			"name":"Козельск"
		},
		{
			"id":1045,
			"name":"Козьмодемьянск"
		},
		{
			"id":1046,
			"name":"Кокошкино"
		},
		{
			"id":1047,
			"name":"Кокшетау"
		},
		{
			"id":1048,
			"name":"Коломна"
		},
		{
			"id":1049,
			"name":"Колпино"
		},
		{
			"id":1050,
			"name":"Колтуши"
		},
		{
			"id":1051,
			"name":"Кольчугино"
		},
		{
			"id":1052,
			"name":"Коммунар"
		},
		{
			"id":1053,
			"name":"Коммунарка"
		},
		{
			"id":1054,
			"name":"Комсомольск-на-Амуре"
		},
		{
			"id":1055,
			"name":"Конаково"
		},
		{
			"id":1056,
			"name":"Кондратова"
		},
		{
			"id":1057,
			"name":"Кондрово"
		},
		{
			"id":1058,
			"name":"Коноша"
		},
		{
			"id":1059,
			"name":"Копейск"
		},
		{
			"id":1060,
			"name":"Коренево"
		},
		{
			"id":1061,
			"name":"Коркино"
		},
		{
			"id":1062,
			"name":"Королев"
		},
		{
			"id":1063,
			"name":"Корсаков"
		},
		{
			"id":1064,
			"name":"Корткерос"
		},
		{
			"id":1065,
			"name":"Костанай"
		},
		{
			"id":1066,
			"name":"Костерево"
		},
		{
			"id":1067,
			"name":"Кострово"
		},
		{
			"id":1068,
			"name":"Кострома"
		},
		{
			"id":1069,
			"name":"Котельники"
		},
		{
			"id":1070,
			"name":"Котельнич"
		},
		{
			"id":1071,
			"name":"Котлас"
		},
		{
			"id":1072,
			"name":"Кохма"
		},
		{
			"id":1073,
			"name":"Красково"
		},
		{
			"id":1074,
			"name":"Красная Пахра"
		},
		{
			"id":1075,
			"name":"Красноармейск"
		},
		{
			"id":1076,
			"name":"Красноборск"
		},
		{
			"id":1077,
			"name":"Красновишерск"
		},
		{
			"id":1078,
			"name":"Красногорск"
		},
		{
			"id":1079,
			"name":"Краснодар"
		},
		{
			"id":1080,
			"name":"Красное Село"
		},
		{
			"id":1081,
			"name":"Краснозатонский"
		},
		{
			"id":1082,
			"name":"Краснознаменск"
		},
		{
			"id":1083,
			"name":"Краснокамск"
		},
		{
			"id":1084,
			"name":"Краснослободск "
		},
		{
			"id":1085,
			"name":"Краснотуринск "
		},
		{
			"id":1086,
			"name":"Красноуральск"
		},
		{
			"id":1087,
			"name":"Красноуфимск "
		},
		{
			"id":1088,
			"name":"Красноярск"
		},
		{
			"id":1089,
			"name":"Красный Чикой"
		},
		{
			"id":1090,
			"name":"Кратово"
		},
		{
			"id":1091,
			"name":"Кривцово"
		},
		{
			"id":1092,
			"name":"Кронштадт"
		},
		{
			"id":1093,
			"name":"Кропоткин"
		},
		{
			"id":1094,
			"name":"Крымск"
		},
		{
			"id":1095,
			"name":"Кстово"
		},
		{
			"id":1096,
			"name":"Кубинка"
		},
		{
			"id":1097,
			"name":"Кувшиново"
		},
		{
			"id":1098,
			"name":"Кудымкар"
		},
		{
			"id":1099,
			"name":"Кузьмоловский"
		},
		{
			"id":1100,
			"name":"Култаево"
		},
		{
			"id":1101,
			"name":"Кунгур"
		},
		{
			"id":1102,
			"name":"Курган"
		},
		{
			"id":1103,
			"name":"Куркино"
		},
		{
			"id":1104,
			"name":"Куровское"
		},
		{
			"id":1105,
			"name":"Курск"
		},
		{
			"id":1106,
			"name":"Курск (Железногорск)"
		},
		{
			"id":1107,
			"name":"Курск (Льгов)"
		},
		{
			"id":1108,
			"name":"Курчатов"
		},
		{
			"id":1109,
			"name":"Куса"
		},
		{
			"id":1110,
			"name":"Кустанай"
		},
		{
			"id":1111,
			"name":"Кушва"
		},
		{
			"id":1112,
			"name":"Кызыл"
		},
		{
			"id":1113,
			"name":"Кыштым"
		},
		{
			"id":1114,
			"name":"Лазаревское"
		},
		{
			"id":1115,
			"name":"Лакинск"
		},
		{
			"id":1116,
			"name":"Лапино"
		},
		{
			"id":1117,
			"name":"Лахта"
		},
		{
			"id":1118,
			"name":"Ленинск-Кузнецкий"
		},
		{
			"id":1119,
			"name":"Лесной"
		},
		{
			"id":1120,
			"name":"Лесной городок"
		},
		{
			"id":1121,
			"name":"Лесосибирск"
		},
		{
			"id":1122,
			"name":"Ликино-Дулево"
		},
		{
			"id":1123,
			"name":"Липецк"
		},
		{
			"id":1124,
			"name":"Лиски"
		},
		{
			"id":1125,
			"name":"Лихославль"
		},
		{
			"id":1126,
			"name":"Лобня"
		},
		{
			"id":1127,
			"name":"Лодейное поле"
		},
		{
			"id":1128,
			"name":"Ломоносов"
		},
		{
			"id":1129,
			"name":"Лосино-Петровский"
		},
		{
			"id":1130,
			"name":"Лотошино"
		},
		{
			"id":1131,
			"name":"Луховицы"
		},
		{
			"id":1132,
			"name":"Лысьва"
		},
		{
			"id":1133,
			"name":"Лыткарино"
		},
		{
			"id":1134,
			"name":"Львовский "
		},
		{
			"id":1135,
			"name":"Люберцы"
		},
		{
			"id":1136,
			"name":"Лянгасово"
		},
		{
			"id":1137,
			"name":"Лянтор"
		},
		{
			"id":1138,
			"name":"Магнитогорск"
		},
		{
			"id":1139,
			"name":"Майкоп"
		},
		{
			"id":1140,
			"name":"Майский"
		},
		{
			"id":1141,
			"name":"Малаховка"
		},
		{
			"id":1142,
			"name":"Малино"
		},
		{
			"id":1143,
			"name":"Малоярославец"
		},
		{
			"id":1144,
			"name":"Малые Вяземы"
		},
		{
			"id":1145,
			"name":"Малышева"
		},
		{
			"id":1146,
			"name":"Марфино"
		},
		{
			"id":1147,
			"name":"Матвейково"
		},
		{
			"id":1148,
			"name":"Мегет"
		},
		{
			"id":1149,
			"name":"Мегион"
		},
		{
			"id":1150,
			"name":"Медвежьи Озера"
		},
		{
			"id":1151,
			"name":"Межгорье"
		},
		{
			"id":1152,
			"name":"Междуреченск"
		},
		{
			"id":1153,
			"name":"Мезень"
		},
		{
			"id":1154,
			"name":"Менделеево"
		},
		{
			"id":1155,
			"name":"Мечниково"
		},
		{
			"id":1156,
			"name":"Миасс"
		},
		{
			"id":1157,
			"name":"Миасское"
		},
		{
			"id":1158,
			"name":"Микунь"
		},
		{
			"id":1159,
			"name":"Минусинск"
		},
		{
			"id":1160,
			"name":"Мисайлово"
		},
		{
			"id":1161,
			"name":"Михайлов"
		},
		{
			"id":1162,
			"name":"Михайловск"
		},
		{
			"id":1163,
			"name":"Михнево"
		},
		{
			"id":1164,
			"name":"Можайск"
		},
		{
			"id":1165,
			"name":"Можга"
		},
		{
			"id":1166,
			"name":"Молоково"
		},
		{
			"id":1167,
			"name":"Монино"
		},
		{
			"id":1168,
			"name":"Московский"
		},
		{
			"id":1169,
			"name":"Мулино"
		},
		{
			"id":1170,
			"name":"Мурино"
		},
		{
			"id":1171,
			"name":"Муром"
		},
		{
			"id":1172,
			"name":"Мытищи"
		},
		{
			"id":1173,
			"name":"Н. Синьково"
		},
		{
			"id":1174,
			"name":"Набережные Челны "
		},
		{
			"id":1175,
			"name":"Назарово"
		},
		{
			"id":1176,
			"name":"Назия"
		},
		{
			"id":1177,
			"name":"Наро-Фоминск"
		},
		{
			"id":1178,
			"name":"Нахабино"
		},
		{
			"id":1179,
			"name":"Находка"
		},
		{
			"id":1180,
			"name":"Невинномыск"
		},
		{
			"id":1181,
			"name":"Невьянск"
		},
		{
			"id":1182,
			"name":"Некрасовский"
		},
		{
			"id":1183,
			"name":"Нефтекамск"
		},
		{
			"id":1184,
			"name":"Нефтеюганск"
		},
		{
			"id":1185,
			"name":"Нижневартовск"
		},
		{
			"id":1186,
			"name":"Нижнекамск"
		},
		{
			"id":1187,
			"name":"Нижнесортымский"
		},
		{
			"id":1188,
			"name":"Нижние серьги"
		},
		{
			"id":1189,
			"name":"Нижний Тагил"
		},
		{
			"id":1190,
			"name":"Нижняя Салда"
		},
		{
			"id":1191,
			"name":"Нов Ляды"
		},
		{
			"id":1192,
			"name":"Новая"
		},
		{
			"id":1193,
			"name":"Новоалександровск"
		},
		{
			"id":1194,
			"name":"Новоалтайск"
		},
		{
			"id":1195,
			"name":"Нововоронеж"
		},
		{
			"id":1196,
			"name":"Новодвинск"
		},
		{
			"id":1197,
			"name":"Новодевяткино"
		},
		{
			"id":1198,
			"name":"Новое Девяткино"
		},
		{
			"id":1199,
			"name":"Новокосино"
		},
		{
			"id":1200,
			"name":"Новокузнецк"
		},
		{
			"id":1201,
			"name":"Новокуйбышевск"
		},
		{
			"id":1202,
			"name":"Новомихайловский"
		},
		{
			"id":1203,
			"name":"Новомичуринск"
		},
		{
			"id":1204,
			"name":"Новомосковск"
		},
		{
			"id":1205,
			"name":"Новопавловская"
		},
		{
			"id":1206,
			"name":"Ново-Переделкино"
		},
		{
			"id":1207,
			"name":"Новопетровское"
		},
		{
			"id":1208,
			"name":"Новороссийск"
		},
		{
			"id":1209,
			"name":"Новоселецкое"
		},
		{
			"id":1210,
			"name":"Новосинеглазова"
		},
		{
			"id":1211,
			"name":"Ново-синьково"
		},
		{
			"id":1212,
			"name":"Новосмолино"
		},
		{
			"id":1213,
			"name":"Новотроицк"
		},
		{
			"id":1214,
			"name":"Новоуральск "
		},
		{
			"id":1215,
			"name":"Новочебоксарск"
		},
		{
			"id":1216,
			"name":"Новый Уренгой"
		},
		{
			"id":1217,
			"name":"Ногинск"
		},
		{
			"id":1218,
			"name":"Нолинск"
		},
		{
			"id":1219,
			"name":"Ноябрьск"
		},
		{
			"id":1220,
			"name":"Нытва"
		},
		{
			"id":1221,
			"name":"Нягань"
		},
		{
			"id":1222,
			"name":"Нязепетровск"
		},
		{
			"id":1223,
			"name":"Няндома"
		},
		{
			"id":1224,
			"name":"Обнинск"
		},
		{
			"id":1225,
			"name":"Обухово"
		},
		{
			"id":1226,
			"name":"Объячево"
		},
		{
			"id":1227,
			"name":"Одинцово"
		},
		{
			"id":1228,
			"name":"Ожерелье"
		},
		{
			"id":1229,
			"name":"Озерск"
		},
		{
			"id":1230,
			"name":"Озерское"
		},
		{
			"id":1231,
			"name":"Озёры"
		},
		{
			"id":1232,
			"name":"Октябрьская"
		},
		{
			"id":1233,
			"name":"Октябрьский"
		},
		{
			"id":1234,
			"name":"Оленино"
		},
		{
			"id":1235,
			"name":"Омск"
		},
		{
			"id":1236,
			"name":"Онега"
		},
		{
			"id":1237,
			"name":"ООО Фаворит"
		},
		{
			"id":1238,
			"name":"Орел"
		},
		{
			"id":1239,
			"name":"Оренбург"
		},
		{
			"id":1240,
			"name":"Орехово-Зуево"
		},
		{
			"id":1241,
			"name":"Орлова"
		},
		{
			"id":1242,
			"name":"Орск"
		},
		{
			"id":1243,
			"name":"Осташков"
		},
		{
			"id":1244,
			"name":"Островцы"
		},
		{
			"id":1245,
			"name":"Отрадное"
		},
		{
			"id":1246,
			"name":"Оханск"
		},
		{
			"id":1247,
			"name":"Очер"
		},
		{
			"id":1248,
			"name":"Павлово"
		},
		{
			"id":1249,
			"name":"Павловск"
		},
		{
			"id":1250,
			"name":"Павловская Слобода"
		},
		{
			"id":1251,
			"name":"Павловский Посад"
		},
		{
			"id":1252,
			"name":"Павлодар"
		},
		{
			"id":1253,
			"name":"Парголово"
		},
		{
			"id":1254,
			"name":"Пенза"
		},
		{
			"id":1255,
			"name":"Первомайское"
		},
		{
			"id":1256,
			"name":"Первомаский"
		},
		{
			"id":1257,
			"name":"Первоуральск"
		},
		{
			"id":1258,
			"name":"Пермь"
		},
		{
			"id":1259,
			"name":"Пестрецы"
		},
		{
			"id":1260,
			"name":"Петергоф"
		},
		{
			"id":1261,
			"name":"Петродворец"
		},
		{
			"id":1262,
			"name":"Петропавловск"
		},
		{
			"id":1263,
			"name":"Петушки"
		},
		{
			"id":1264,
			"name":"Печора"
		},
		{
			"id":1265,
			"name":"Пироговский"
		},
		{
			"id":1266,
			"name":"Пласт"
		},
		{
			"id":1267,
			"name":"Плесецк"
		},
		{
			"id":1268,
			"name":"Поварово"
		},
		{
			"id":1269,
			"name":"Подольск"
		},
		{
			"id":1270,
			"name":"Пойковский"
		},
		{
			"id":1271,
			"name":"Покров"
		},
		{
			"id":1272,
			"name":"Полазна"
		},
		{
			"id":1273,
			"name":"Полевской "
		},
		{
			"id":1274,
			"name":"Правдинский"
		},
		{
			"id":1275,
			"name":"Придонской"
		},
		{
			"id":1276,
			"name":"Прокопьевск"
		},
		{
			"id":1277,
			"name":"Протвино"
		},
		{
			"id":1278,
			"name":"Путилково"
		},
		{
			"id":1279,
			"name":"Пушкин"
		},
		{
			"id":1280,
			"name":"Пушкино"
		},
		{
			"id":1281,
			"name":"Пущино"
		},
		{
			"id":1282,
			"name":"Пятигорск"
		},
		{
			"id":1283,
			"name":"Радужный"
		},
		{
			"id":1284,
			"name":"Развилка"
		},
		{
			"id":1285,
			"name":"Раменское"
		},
		{
			"id":1286,
			"name":"Растуново"
		},
		{
			"id":1287,
			"name":"Ревда"
		},
		{
			"id":1288,
			"name":"Реж"
		},
		{
			"id":1289,
			"name":"Реутов"
		},
		{
			"id":1290,
			"name":"Реутор"
		},
		{
			"id":1291,
			"name":"Рефтинский"
		},
		{
			"id":1292,
			"name":"Ржев"
		},
		{
			"id":1293,
			"name":"Рогачево"
		},
		{
			"id":1294,
			"name":"Родники"
		},
		{
			"id":1295,
			"name":"Россошь"
		},
		{
			"id":1296,
			"name":"Ростов"
		},
		{
			"id":1297,
			"name":"Ростов на Дону"
		},
		{
			"id":1298,
			"name":"Рубцовск"
		},
		{
			"id":1299,
			"name":"Руза"
		},
		{
			"id":1300,
			"name":"Рыбинск"
		},
		{
			"id":1301,
			"name":"Рыбное"
		},
		{
			"id":1302,
			"name":"Рязань"
		},
		{
			"id":1303,
			"name":"Салават"
		},
		{
			"id":1304,
			"name":"Саранск"
		},
		{
			"id":1305,
			"name":"Сарапул"
		},
		{
			"id":1306,
			"name":"Саратов"
		},
		{
			"id":1307,
			"name":"Саров"
		},
		{
			"id":1308,
			"name":"Сарс"
		},
		{
			"id":1309,
			"name":"Сатка"
		},
		{
			"id":1310,
			"name":"Саяногорск"
		},
		{
			"id":1311,
			"name":"СББЖ ТиАНО Саларьево"
		},
		{
			"id":1312,
			"name":"СББЖ ТиАНО Яковлевская рай Новомосковский"
		},
		{
			"id":1313,
			"name":"Свердловка"
		},
		{
			"id":1314,
			"name":"Свердлово"
		},
		{
			"id":1315,
			"name":"Светлоград"
		},
		{
			"id":1316,
			"name":"Севастополь"
		},
		{
			"id":1317,
			"name":"Северодвинск"
		},
		{
			"id":1318,
			"name":"Североуральск "
		},
		{
			"id":1319,
			"name":"Северск"
		},
		{
			"id":1320,
			"name":"Селятино"
		},
		{
			"id":1321,
			"name":"Семилуки"
		},
		{
			"id":1322,
			"name":"Семфирополь"
		},
		{
			"id":1323,
			"name":"Сергиев Посад"
		},
		{
			"id":1324,
			"name":"Серов"
		},
		{
			"id":1325,
			"name":"Серпухов"
		},
		{
			"id":1326,
			"name":"Сертолово"
		},
		{
			"id":1327,
			"name":"Сестрорецк"
		},
		{
			"id":1328,
			"name":"Сибай"
		},
		{
			"id":1329,
			"name":"Сим"
		},
		{
			"id":1330,
			"name":"Симферополь"
		},
		{
			"id":1331,
			"name":"Синячиха"
		},
		{
			"id":1332,
			"name":"Славгород"
		},
		{
			"id":1333,
			"name":"Славянск-на-Кубани"
		},
		{
			"id":1334,
			"name":"Слободской"
		},
		{
			"id":1335,
			"name":"Смоленск"
		},
		{
			"id":1336,
			"name":"Снегири"
		},
		{
			"id":1337,
			"name":"Снежинск"
		},
		{
			"id":1338,
			"name":"Сов. Гавань"
		},
		{
			"id":1339,
			"name":"Совхоз"
		},
		{
			"id":1340,
			"name":"совхоз им. Ленина"
		},
		{
			"id":1341,
			"name":"Совхоз Останкино"
		},
		{
			"id":1342,
			"name":"Соликамск"
		},
		{
			"id":1343,
			"name":"Солнечногорск"
		},
		{
			"id":1344,
			"name":"Солнцево"
		},
		{
			"id":1345,
			"name":"Сосенки"
		},
		{
			"id":1346,
			"name":"Сосново"
		},
		{
			"id":1347,
			"name":"Сосновоборск"
		},
		{
			"id":1348,
			"name":"Сосновый Бор"
		},
		{
			"id":1349,
			"name":"Сосногорск"
		},
		{
			"id":1350,
			"name":"Софрино"
		},
		{
			"id":1351,
			"name":"Сочи"
		},
		{
			"id":1352,
			"name":"Спасск"
		},
		{
			"id":1353,
			"name":"Среднеуральск"
		},
		{
			"id":1354,
			"name":"Средняя Ахтуба "
		},
		{
			"id":1355,
			"name":"ст. Анапская"
		},
		{
			"id":1356,
			"name":"ст. Варениковская"
		},
		{
			"id":1357,
			"name":"ст. Выселки"
		},
		{
			"id":1358,
			"name":"ст. Динская"
		},
		{
			"id":1359,
			"name":"Ст. Елизаветинская"
		},
		{
			"id":1360,
			"name":"ст. Калининская"
		},
		{
			"id":1361,
			"name":"ст. Курская"
		},
		{
			"id":1362,
			"name":"ст. Ленинградская"
		},
		{
			"id":1363,
			"name":"ст. Новопокровская"
		},
		{
			"id":1364,
			"name":"ст. Павловская"
		},
		{
			"id":1365,
			"name":"ст. Полтавская"
		},
		{
			"id":1366,
			"name":"ст. Северская"
		},
		{
			"id":1367,
			"name":"ст. Суворовская"
		},
		{
			"id":1368,
			"name":"ст. С-щербиновская"
		},
		{
			"id":1369,
			"name":"ст.Ипатово"
		},
		{
			"id":1370,
			"name":"ст.Каневская"
		},
		{
			"id":1371,
			"name":"ст.Обухово"
		},
		{
			"id":1372,
			"name":"Ст.Северская"
		},
		{
			"id":1373,
			"name":"ст.Староминская"
		},
		{
			"id":1374,
			"name":"Ставрополь"
		},
		{
			"id":1375,
			"name":"Старая"
		},
		{
			"id":1376,
			"name":"Старая Купавна"
		},
		{
			"id":1377,
			"name":"Старый Оскол"
		},
		{
			"id":1378,
			"name":"Стерлитамак"
		},
		{
			"id":1379,
			"name":"Стрежевой"
		},
		{
			"id":1380,
			"name":"Стрельна"
		},
		{
			"id":1381,
			"name":"Строитель"
		},
		{
			"id":1382,
			"name":"Струнино"
		},
		{
			"id":1383,
			"name":"Ступино"
		},
		{
			"id":1384,
			"name":"Суздаль"
		},
		{
			"id":1385,
			"name":"Супсех"
		},
		{
			"id":1386,
			"name":"Сургут"
		},
		{
			"id":1387,
			"name":"Сухой Лог"
		},
		{
			"id":1388,
			"name":"Сыктывкар"
		},
		{
			"id":1389,
			"name":"Сылва"
		},
		{
			"id":1390,
			"name":"Сысерть "
		},
		{
			"id":1391,
			"name":"Тавда"
		},
		{
			"id":1392,
			"name":"Талдом"
		},
		{
			"id":1393,
			"name":"Талица"
		},
		{
			"id":1394,
			"name":"Тамбов"
		},
		{
			"id":1395,
			"name":"Тарко-Сале"
		},
		{
			"id":1396,
			"name":"Таруса"
		},
		{
			"id":1397,
			"name":"Тверь"
		},
		{
			"id":1398,
			"name":"Тейково"
		},
		{
			"id":1399,
			"name":"Тельмана"
		},
		{
			"id":1400,
			"name":"Темиртау"
		},
		{
			"id":1401,
			"name":"Темрюк"
		},
		{
			"id":1402,
			"name":"Тимашевск"
		},
		{
			"id":1403,
			"name":"Тимоново"
		},
		{
			"id":1404,
			"name":"Тихорецк"
		},
		{
			"id":1405,
			"name":"Тобольск"
		},
		{
			"id":1406,
			"name":"Тольятти"
		},
		{
			"id":1407,
			"name":"Томилино"
		},
		{
			"id":1408,
			"name":"Томск"
		},
		{
			"id":1409,
			"name":"Топки"
		},
		{
			"id":1410,
			"name":"Торжок"
		},
		{
			"id":1411,
			"name":"Трехгорный"
		},
		{
			"id":1412,
			"name":"Троицк"
		},
		{
			"id":1413,
			"name":"Троицко-Печерск"
		},
		{
			"id":1414,
			"name":"Трудовая"
		},
		{
			"id":1415,
			"name":"Туапсе"
		},
		{
			"id":1416,
			"name":"Туймазы"
		},
		{
			"id":1417,
			"name":"Тула"
		},
		{
			"id":1418,
			"name":"Тума"
		},
		{
			"id":1419,
			"name":"Туринская Слобода "
		},
		{
			"id":1420,
			"name":"Тучково"
		},
		{
			"id":1421,
			"name":"Тымовск"
		},
		{
			"id":1422,
			"name":"Тюмень"
		},
		{
			"id":1423,
			"name":"Углегорск"
		},
		{
			"id":1424,
			"name":"Углезаводск"
		},
		{
			"id":1425,
			"name":"Удельная"
		},
		{
			"id":1426,
			"name":"Удомля"
		},
		{
			"id":1427,
			"name":"Узловая"
		},
		{
			"id":1428,
			"name":"Улан-Удэ"
		},
		{
			"id":1429,
			"name":"Ульяновка"
		},
		{
			"id":1430,
			"name":"Урай"
		},
		{
			"id":1431,
			"name":"Уральский"
		},
		{
			"id":1432,
			"name":"Урдома"
		},
		{
			"id":1433,
			"name":"Усолье-Сибирское"
		},
		{
			"id":1434,
			"name":"Уссурийск"
		},
		{
			"id":1435,
			"name":"Усть Лабинск"
		},
		{
			"id":1436,
			"name":"Усть-Каменогорск"
		},
		{
			"id":1437,
			"name":"Усть-Катав"
		},
		{
			"id":1438,
			"name":"Усть-качка"
		},
		{
			"id":1439,
			"name":"Устьяны"
		},
		{
			"id":1440,
			"name":"Уфа"
		},
		{
			"id":1441,
			"name":"Ухта"
		},
		{
			"id":1442,
			"name":"Ушакова"
		},
		{
			"id":1443,
			"name":"Ушья"
		},
		{
			"id":1444,
			"name":"Фершанпенуаз"
		},
		{
			"id":1445,
			"name":"Фокино"
		},
		{
			"id":1446,
			"name":"Фролы"
		},
		{
			"id":1447,
			"name":"Фрязино"
		},
		{
			"id":1448,
			"name":"Хабаровск"
		},
		{
			"id":1449,
			"name":"Ханты-Мансийск"
		},
		{
			"id":1450,
			"name":"Химки"
		},
		{
			"id":1451,
			"name":"Холмогоры"
		},
		{
			"id":1452,
			"name":"Холмск"
		},
		{
			"id":1453,
			"name":"Хомутово"
		},
		{
			"id":1454,
			"name":"Хотьково"
		},
		{
			"id":1455,
			"name":"Хохол"
		},
		{
			"id":1456,
			"name":"Чайковский"
		},
		{
			"id":1457,
			"name":"Часцы"
		},
		{
			"id":1458,
			"name":"Чебаркуль"
		},
		{
			"id":1459,
			"name":"Чебоксары"
		},
		{
			"id":1460,
			"name":"Челябинск"
		},
		{
			"id":1461,
			"name":"Чердынь"
		},
		{
			"id":1462,
			"name":"Черемхово"
		},
		{
			"id":1463,
			"name":"Череповец"
		},
		{
			"id":1464,
			"name":"Черная грязь"
		},
		{
			"id":1465,
			"name":"Черноголовка"
		},
		{
			"id":1466,
			"name":"Черногорск"
		},
		{
			"id":1467,
			"name":"Чесноково"
		},
		{
			"id":1468,
			"name":"Чехов"
		},
		{
			"id":1469,
			"name":"Чита"
		},
		{
			"id":1470,
			"name":"Чишмы"
		},
		{
			"id":1471,
			"name":"Чкаловский"
		},
		{
			"id":1472,
			"name":"Чулково"
		},
		{
			"id":1473,
			"name":"Чупряково"
		},
		{
			"id":1474,
			"name":"Чусовой"
		},
		{
			"id":1475,
			"name":"Шадринск"
		},
		{
			"id":1476,
			"name":"Шатура"
		},
		{
			"id":1477,
			"name":"Шаховская"
		},
		{
			"id":1478,
			"name":"Шахунья"
		},
		{
			"id":1479,
			"name":"Шебекино"
		},
		{
			"id":1480,
			"name":"Шелехов"
		},
		{
			"id":1481,
			"name":"Шенкурск"
		},
		{
			"id":1482,
			"name":"Шилово"
		},
		{
			"id":1483,
			"name":"Шлиссельбург"
		},
		{
			"id":1484,
			"name":"Шолохово"
		},
		{
			"id":1485,
			"name":"Шушары"
		},
		{
			"id":1486,
			"name":"Шушенское"
		},
		{
			"id":1487,
			"name":"Шуя"
		},
		{
			"id":1488,
			"name":"Шымкент"
		},
		{
			"id":1489,
			"name":"Щекино"
		},
		{
			"id":1490,
			"name":"Щелково"
		},
		{
			"id":1491,
			"name":"Щелково 3"
		},
		{
			"id":1492,
			"name":"Щербинка"
		},
		{
			"id":1493,
			"name":"Щучье"
		},
		{
			"id":1494,
			"name":"Электрогорск"
		},
		{
			"id":1495,
			"name":"Электросталь"
		},
		{
			"id":1496,
			"name":"Электроугли"
		},
		{
			"id":1497,
			"name":"Элиста"
		},
		{
			"id":1498,
			"name":"Энгельс"
		},
		{
			"id":1499,
			"name":"Юбилейный"
		},
		{
			"id":1500,
			"name":"Югорск "
		},
		{
			"id":1501,
			"name":"Южно-Сахалинск"
		},
		{
			"id":1502,
			"name":"Южноуральск"
		},
		{
			"id":1503,
			"name":"Южный"
		},
		{
			"id":1504,
			"name":"Юрьевец"
		},
		{
			"id":1505,
			"name":"Юрюзань"
		},
		{
			"id":1506,
			"name":"Яблоновский"
		},
		{
			"id":1507,
			"name":"Ядрин"
		},
		{
			"id":1508,
			"name":"Яйва"
		},
		{
			"id":1509,
			"name":"Ялта"
		},
		{
			"id":1510,
			"name":"Ялуторовск г"
		},
		{
			"id":1511,
			"name":"Ям"
		},
		{
			"id":1512,
			"name":"Ярославль"
		},
		{
			"id":1513,
			"name":"Ясный"
		},
		{
			"id":1514,
			"name":"Яхрома"
		}
	],
	"objects":{
	},
	"currentLocation":[
		"Российская Федерация",
		"Челябинск"
	]
}